weather_api/__init__.py
weather_api/weather.py
weather_api_for_python-0.1.dist-info/LICENSE
weather_api_for_python-0.1.dist-info/METADATA
weather_api_for_python-0.1.dist-info/WHEEL
weather_api_for_python-0.1.dist-info/top_level.txt
weather_api_for_python-0.1.dist-info/RECORD
