Metadata-Version: 2.1
Name: weather-api-for-python
Version: 0.1
Summary: API для получения погоды
Home-page: https://github.com/daniilkrestyaninov/weather_for_python
Author: Даниил
Author-email: krestaninovdaniil@gmail.com
Classifier: Programming Language :: Python :: 3
Classifier: License :: OSI Approved :: MIT License
Classifier: Operating System :: OS Independent
Requires-Python: >=3.7
License-File: LICENSE
Requires-Dist: requests
